owmpy/__init__.py
owmpy/py.typed
owmpy/core/__init__.py
owmpy/core/api_exception.py
owmpy/core/base_client.py
owmpy/current/__init__.py
owmpy/current/client.py
owmpy/current/response/__init__.py
owmpy/current/response/clouds.py
owmpy/current/response/coord.py
owmpy/current/response/main.py
owmpy/current/response/rain.py
owmpy/current/response/response.py
owmpy/current/response/sys.py
owmpy/current/response/weather.py
owmpy/current/response/wind.py
owmpy/utils/__init__.py
owmpy/utils/short_long.py
owmpy/utils/standard_units.py
owmpy/utils/units.py
owmpy-1.0.5.dist-info/LICENSE
owmpy-1.0.5.dist-info/METADATA
owmpy-1.0.5.dist-info/WHEEL
owmpy-1.0.5.dist-info/top_level.txt
owmpy-1.0.5.dist-info/RECORD
