Metadata-Version: 2.1
Name: owmpy
Version: 1.0.5
Summary: A wrapper for the OpenWeatherMap API
Home-page: https://github.com/ernieIzde8ski/open_weather_mappy
Author: Ernest Izdebski
License: MIT
Classifier: Programming Language :: Python :: 3
Classifier: License :: OSI Approved :: MIT License
Classifier: Operating System :: OS Independent
License-File: LICENSE
Requires-Dist: aiohttp >=3.7.4
Requires-Dist: pydantic >=1.9.0
